Examen_Libreria/__init__.py
Examen_Libreria/books_new.csv
Examen_Libreria/consulta_libros.py
Examen_Libreria-1.0.0.dist-info/METADATA
Examen_Libreria-1.0.0.dist-info/WHEEL
Examen_Libreria-1.0.0.dist-info/top_level.txt
Examen_Libreria-1.0.0.dist-info/RECORD
